[
  {
    "originalTitle": "いたずら天使チッポちゃん",
    "chineseTitle": "",
    "titleMsg": "",
    "startDate": "Mar 30, 1971, 12:00:00 AM",
    "endDate": "Dec 31, 1971, 12:00:00 AM",
    "videoType": "電視動畫",
    "company": "フジテレビエンタープライズ",
    "episodes": 240,
    "year": 1971
  },
  {
    "originalTitle": "動物村ものがたり",
    "chineseTitle": "動物村物語",
    "titleMsg": "",
    "startDate": "Mar 30, 1971, 12:00:00 AM",
    "endDate": "Jul 21, 1971, 12:00:00 AM",
    "videoType": "電視動畫",
    "company": "TCJ",
    "episodes": 100,
    "year": 1971
  },
  {
    "originalTitle": "あしたのジョー",
    "chineseTitle": "小拳王",
    "titleMsg": "",
    "startDate": "Apr 1, 1971, 12:00:00 AM",
    "endDate": "Apr 29, 1971, 12:00:00 AM",
    "videoType": "電視動畫",
    "company": "蟲Production",
    "episodes": 79,
    "year": 1971
  },
  {
    "originalTitle": "ばくはつ五郎",
    "chineseTitle": "",
    "titleMsg": "",
    "startDate": "Apr 3, 1971, 12:00:00 AM",
    "endDate": "Sep 25, 1971, 12:00:00 AM",
    "videoType": "電視動畫",
    "company": "TCJ動畫センター",
    "episodes": 26,
    "year": 1971
  },
  {
    "originalTitle": "おたのしみアニメ劇場",
    "chineseTitle": "",
    "titleMsg": "",
    "startDate": "Apr 5, 1971, 12:00:00 AM",
    "endDate": "Sep 27, 1971, 12:00:00 AM",
    "videoType": "電視動畫",
    "company": "零工作室",
    "episodes": 26,
    "year": 1971
  },
  {
    "originalTitle": "昆虫物語 みなしごハッチ",
    "chineseTitle": "小蜜蜂（昆蟲物語 孤兒哈奇）",
    "titleMsg": "",
    "startDate": "Apr 7, 1971, 12:00:00 AM",
    "endDate": "Dec 28, 1971, 12:00:00 AM",
    "videoType": "電視動畫",
    "company": "龍之子",
    "episodes": 91,
    "year": 1971
  },
  {
    "originalTitle": "赤き血のイレブン",
    "chineseTitle": "足球健將",
    "titleMsg": "",
    "startDate": "Apr 13, 1971, 12:00:00 AM",
    "endDate": "Apr 5, 1971, 12:00:00 AM",
    "videoType": "電視動畫",
    "company": "東京テレビ動畫",
    "episodes": 52,
    "year": 1971
  },
  {
    "originalTitle": "日本誕生",
    "chineseTitle": "日本誕生",
    "titleMsg": "",
    "startDate": "Jun 10, 1971, 12:00:00 AM",
    "endDate": "Oct 24, 1971, 12:00:00 AM",
    "videoType": "電視動畫",
    "company": "蟲Production",
    "episodes": 5,
    "year": 1971
  },
  {
    "originalTitle": "キリンものしり大学・マンガ人物史",
    "chineseTitle": "",
    "titleMsg": "",
    "startDate": "Aug 3, 1971, 12:00:00 AM",
    "endDate": "Sep 30, 1971, 12:00:00 AM",
    "videoType": "電視動畫",
    "company": "オフィス・ユニ",
    "episodes": 366,
    "year": 1971
  },
  {
    "originalTitle": "男どアホウ甲子園",
    "chineseTitle": "",
    "titleMsg": "",
    "startDate": "Sep 28, 1971, 12:00:00 AM",
    "endDate": "Mar 27, 1971, 12:00:00 AM",
    "videoType": "電視動畫",
    "company": "東京テレビ動畫",
    "episodes": 156,
    "year": 1971
  },
  {
    "originalTitle": "キックの鬼",
    "chineseTitle": "無影腳",
    "titleMsg": "",
    "startDate": "Oct 2, 1971, 12:00:00 AM",
    "endDate": "Mar 26, 1971, 12:00:00 AM",
    "videoType": "電視動畫",
    "company": "東映動畫",
    "episodes": 26,
    "year": 1971
  },
  {
    "originalTitle": "いじわるばあさん",
    "chineseTitle": "",
    "titleMsg": "",
    "startDate": "Oct 3, 1971, 12:00:00 AM",
    "endDate": "Aug 18, 1971, 12:00:00 AM",
    "videoType": "電視動畫",
    "company": "ナック",
    "episodes": 40,
    "year": 1971
  },
  {
    "originalTitle": "いなかっぺ大将",
    "chineseTitle": "鄉下仔出城",
    "titleMsg": "",
    "startDate": "Oct 4, 1971, 12:00:00 AM",
    "endDate": "Sep 24, 1972, 12:00:00 AM",
    "videoType": "電視動畫",
    "company": "龍之子",
    "episodes": 208,
    "year": 1971
  },
  {
    "originalTitle": "のらくろ",
    "chineseTitle": "小黑炭",
    "titleMsg": "",
    "startDate": "Oct 5, 1971, 12:00:00 AM",
    "endDate": "Mar 29, 1971, 12:00:00 AM",
    "videoType": "電視動畫",
    "company": "TCJ動畫センター",
    "episodes": 26,
    "year": 1971
  },
  {
    "originalTitle": "われらサラリーマン党",
    "chineseTitle": "",
    "titleMsg": "",
    "startDate": "Oct 7, 1971, 12:00:00 AM",
    "endDate": "Mar 31, 1971, 12:00:00 AM",
    "videoType": "電視動畫",
    "company": "P Productions",
    "episodes": 26,
    "year": 1971
  },
  {
    "originalTitle": "魔法のマコちゃん",
    "chineseTitle": "魔法人魚真子",
    "titleMsg": "",
    "startDate": "Nov 2, 1971, 12:00:00 AM",
    "endDate": "Sep 27, 1971, 12:00:00 AM",
    "videoType": "電視動畫",
    "company": "東映動畫",
    "episodes": 48,
    "year": 1971
  },
  {
    "originalTitle": "ちびっ子レミと名犬カピ",
    "chineseTitle": "苦兒流浪記",
    "titleMsg": "孤兒雷米與名犬卡比（原作：）",
    "startDate": "Mar 17, 1972, 12:00:00 AM",
    "videoType": "動畫電影",
    "hasChineseWikiLink": true,
    "year": 1972
  },
  {
    "originalTitle": "タイガーマスク",
    "chineseTitle": "虎面人（TV版第9-10話再編集）",
    "titleMsg": "",
    "startDate": "Mar 17, 1972, 12:00:00 AM",
    "videoType": "動畫電影",
    "hasChineseWikiLink": false,
    "year": 1972
  },
  {
    "originalTitle": "ひみつのアッコちゃん 「ばんざいペットくん」",
    "chineseTitle": "甜蜜小天使 TV版第39話",
    "titleMsg": "",
    "startDate": "Mar 17, 1972, 12:00:00 AM",
    "videoType": "動畫電影",
    "hasChineseWikiLink": false,
    "year": 1972
  },
  {
    "originalTitle": "チュウチュウバンバン",
    "chineseTitle": "",
    "titleMsg": "",
    "startDate": "Mar 17, 1972, 12:00:00 AM",
    "videoType": "動畫電影",
    "hasChineseWikiLink": false,
    "year": 1972
  },
  {
    "originalTitle": "アタックNo.1",
    "chineseTitle": "排球甜心（TV版再編集）",
    "titleMsg": "",
    "startDate": "Mar 21, 1972, 12:00:00 AM",
    "videoType": "動畫電影",
    "hasChineseWikiLink": false,
    "year": 1972
  },
  {
    "originalTitle": "巨人の星 大リーグボール",
    "chineseTitle": "巨人之星（TV版第70-77話再編集）",
    "titleMsg": "",
    "startDate": "Mar 21, 1972, 12:00:00 AM",
    "videoType": "動畫電影",
    "hasChineseWikiLink": false,
    "year": 1972
  },
  {
    "originalTitle": "やさしいライオン",
    "chineseTitle": "",
    "titleMsg": "",
    "startDate": "Mar 21, 1972, 12:00:00 AM",
    "videoType": "動畫電影",
    "hasChineseWikiLink": false,
    "year": 1972
  },
  {
    "originalTitle": "海底3万マイル",
    "chineseTitle": "海底3萬里",
    "titleMsg": "",
    "startDate": "Jul 19, 1972, 12:00:00 AM",
    "videoType": "動畫電影",
    "hasChineseWikiLink": false,
    "year": 1972
  },
  {
    "originalTitle": "タイガーマスク 「ふく面リーグ戦」",
    "chineseTitle": "虎面人（TV版第23-26話再編集）",
    "titleMsg": "",
    "startDate": "Jul 19, 1972, 12:00:00 AM",
    "videoType": "動畫電影",
    "hasChineseWikiLink": false,
    "year": 1972
  },
  {
    "originalTitle": "ひみつのアッコちゃん 「涙の回転レシーブ」",
    "chineseTitle": "甜蜜小天使 TV版第77話",
    "titleMsg": "",
    "startDate": "Jul 19, 1972, 12:00:00 AM",
    "videoType": "動畫電影",
    "hasChineseWikiLink": false,
    "year": 1972
  },
  {
    "originalTitle": "もーれつア太郎 「ニャロメの子守唄 その1・その2」",
    "chineseTitle": "隔離左右有隻鬼 TV版第63話",
    "titleMsg": "",
    "startDate": "Jul 19, 1972, 12:00:00 AM",
    "videoType": "動畫電影",
    "hasChineseWikiLink": false,
    "year": 1972
  },
  {
    "originalTitle": "アタックNo.1 涙の回転レシーブ",
    "chineseTitle": "排球甜心（TV版再編集）",
    "titleMsg": "",
    "startDate": "Aug 1, 1972, 12:00:00 AM",
    "videoType": "動畫電影",
    "hasChineseWikiLink": false,
    "year": 1972
  },
  {
    "originalTitle": "巨人の星 宿命の対決",
    "chineseTitle": "巨人之星（TV版第79-83話再編集）",
    "titleMsg": "",
    "startDate": "Aug 1, 1972, 12:00:00 AM",
    "videoType": "動畫電影",
    "hasChineseWikiLink": false,
    "year": 1972
  },
  {
    "originalTitle": "クレオパトラ",
    "chineseTitle": "埃及艷后",
    "titleMsg": "",
    "startDate": "Sep 15, 1972, 12:00:00 AM",
    "videoType": "動畫電影",
    "company": "蟲Production",
    "year": 1972
  },
  {
    "originalTitle": "アタックNo.1 涙の世界選手権",
    "chineseTitle": "排球甜心（TV版再編集）",
    "titleMsg": "",
    "startDate": "Dec 19, 1972, 12:00:00 AM",
    "videoType": "動畫電影",
    "hasChineseWikiLink": false,
    "year": 1972
  },
  {
    "originalTitle": "昆虫物語 みなしごハッチ",
    "chineseTitle": "小蜜蜂（TV版第1話）",
    "titleMsg": "",
    "startDate": "Dec 19, 1972, 12:00:00 AM",
    "videoType": "動畫電影",
    "hasChineseWikiLink": false,
    "year": 1972
  },
  {
    "originalTitle": "カバトット",
    "chineseTitle": "烏龍冤家",
    "titleMsg": "",
    "startDate": "Jan 1, 1973, 12:00:00 AM",
    "endDate": "Sep 30, 1972, 12:00:00 AM",
    "videoType": "電視動畫",
    "company": "龍之子",
    "episodes": 300,
    "year": 1973
  },
  {
    "originalTitle": "アンデルセン物語",
    "chineseTitle": "安徒生童話故事",
    "titleMsg": "",
    "startDate": "Jan 3, 1973, 12:00:00 AM",
    "endDate": "Dec 26, 1973, 12:00:00 AM",
    "videoType": "電視動畫",
    "company": "蟲Production",
    "episodes": 52,
    "year": 1973
  },
  {
    "originalTitle": "珍豪ムチャ兵衛",
    "chineseTitle": "",
    "titleMsg": "",
    "startDate": "Feb 15, 1973, 12:00:00 AM",
    "endDate": "Mar 22, 1973, 12:00:00 AM",
    "videoType": "電視動畫",
    "company": "東京電影",
    "episodes": 26,
    "year": 1973
  },
  {
    "originalTitle": "決断",
    "chineseTitle": "決斷",
    "titleMsg": "",
    "startDate": "Apr 3, 1973, 12:00:00 AM",
    "endDate": "Sep 25, 1973, 12:00:00 AM",
    "videoType": "電視動畫",
    "company": "龍之子",
    "episodes": 26,
    "year": 1973
  },
  {
    "originalTitle": "さすらいの太陽",
    "chineseTitle": "飄泊的太陽",
    "titleMsg": "",
    "startDate": "Apr 8, 1973, 12:00:00 AM",
    "endDate": "Sep 30, 1973, 12:00:00 AM",
    "videoType": "電視動畫",
    "company": "蟲Production",
    "episodes": 26,
    "year": 1973
  },
  {
    "originalTitle": "新オバケのQ太郎",
    "chineseTitle": "新Q太郎",
    "titleMsg": "",
    "startDate": "Sep 1, 1973, 12:00:00 AM",
    "endDate": "Dec 27, 1972, 12:00:00 AM",
    "videoType": "電視動畫",
    "company": "東京電影オカスタジオ",
    "episodes": 70,
    "year": 1973
  },
  {
    "originalTitle": "天才バカボン",
    "chineseTitle": "天才妙老爹",
    "titleMsg": "",
    "startDate": "Sep 25, 1973, 12:00:00 AM",
    "endDate": "Jun 24, 1972, 12:00:00 AM",
    "videoType": "電視動畫",
    "company": "東京電影",
    "episodes": 40,
    "year": 1973
  },
  {
    "originalTitle": "世界ものしり旅行",
    "chineseTitle": "",
    "titleMsg": "",
    "startDate": "Oct 1, 1973, 12:00:00 AM",
    "endDate": "Dec 31, 1974, 12:00:00 AM",
    "videoType": "電視動畫",
    "company": "オフィス・ユニ",
    "episodes": 1006,
    "year": 1973
  },
  {
    "originalTitle": "ふしぎなメルモ",
    "chineseTitle": "神化嬌嬌女",
    "titleMsg": "",
    "startDate": "Oct 3, 1973, 12:00:00 AM",
    "endDate": "Mar 26, 1972, 12:00:00 AM",
    "videoType": "電視動畫",
    "company": "手塚Production",
    "episodes": 26,
    "year": 1973
  },
  {
    "originalTitle": "さるとびエッちゃん",
    "chineseTitle": "神奇小丫頭",
    "titleMsg": "",
    "startDate": "Oct 4, 1973, 12:00:00 AM",
    "endDate": "Mar 27, 1972, 12:00:00 AM",
    "videoType": "電視動畫",
    "company": "東映動畫",
    "episodes": 26,
    "year": 1973
  },
  {
    "originalTitle": "アパッチ野球軍",
    "chineseTitle": "阿帕契野球軍",
    "titleMsg": "",
    "startDate": "Oct 6, 1973, 12:00:00 AM",
    "endDate": "Mar 29, 1972, 12:00:00 AM",
    "videoType": "電視動畫",
    "company": "東映動畫",
    "episodes": 26,
    "year": 1973
  },
  {
    "originalTitle": "国松さまのお通りだい",
    "chineseTitle": "萬能旋風兒",
    "titleMsg": "",
    "startDate": "Oct 6, 1973, 12:00:00 AM",
    "endDate": "Sep 25, 1972, 12:00:00 AM",
    "videoType": "電視動畫",
    "company": "蟲Pro",
    "episodes": 46,
    "year": 1973
  },
  {
    "originalTitle": "ゲゲゲの鬼太郎",
    "chineseTitle": "鬼太郎",
    "titleMsg": "（第2作）",
    "startDate": "Oct 7, 1973, 12:00:00 AM",
    "endDate": "Sep 28, 1972, 12:00:00 AM",
    "videoType": "電視動畫",
    "company": "東映動畫",
    "episodes": 45,
    "year": 1973
  },
  {
    "originalTitle": "新スカイヤーズ5",
    "chineseTitle": "飛天五虎將",
    "titleMsg": "",
    "startDate": "Oct 7, 1973, 12:00:00 AM",
    "endDate": "Mar 30, 1972, 12:00:00 AM",
    "videoType": "電視動畫",
    "company": "TCJ動畫センター",
    "episodes": 26,
    "year": 1973
  },
  {
    "originalTitle": "ルパン三世",
    "chineseTitle": "魯邦三世",
    "titleMsg": "（第1作）",
    "startDate": "Oct 24, 1973, 12:00:00 AM",
    "endDate": "Mar 26, 1972, 12:00:00 AM",
    "videoType": "電視動畫",
    "company": "東京電影",
    "episodes": 23,
    "year": 1973
  },
  {
    "originalTitle": "原始少年リュウ",
    "chineseTitle": "小泰山",
    "titleMsg": "",
    "startDate": "Oct 30, 1973, 12:00:00 AM",
    "endDate": "Mar 25, 1972, 12:00:00 AM",
    "videoType": "電視動畫",
    "company": "東映動畫",
    "episodes": 22,
    "year": 1973
  },
  {
    "originalTitle": "アタックNo.1 涙の不死鳥",
    "chineseTitle": "排球甜心（TV版再編集）",
    "titleMsg": "",
    "startDate": "Mar 17, 1974, 12:00:00 AM",
    "videoType": "動畫電影",
    "hasChineseWikiLink": false,
    "year": 1974
  },
  {
    "originalTitle": "ムーミン",
    "chineseTitle": "嚕嚕米（TV版第7話）",
    "titleMsg": "",
    "startDate": "Mar 17, 1974, 12:00:00 AM",
    "videoType": "動畫電影",
    "hasChineseWikiLink": false,
    "year": 1974
  },
  {
    "originalTitle": "いなかっぺ大将",
    "chineseTitle": "鄉下仔出城（TV版再編集）",
    "titleMsg": "",
    "startDate": "Mar 17, 1974, 12:00:00 AM",
    "videoType": "動畫電影",
    "hasChineseWikiLink": false,
    "year": 1974
  },
  {
    "originalTitle": "みなしごハッチ お月さまのママ",
    "chineseTitle": "小蜜蜂 TV版第36話",
    "titleMsg": "",
    "startDate": "Mar 17, 1974, 12:00:00 AM",
    "videoType": "動畫電影",
    "hasChineseWikiLink": false,
    "year": 1974
  },
  {
    "originalTitle": "どうぶつ宝島",
    "chineseTitle": "動物金銀島",
    "titleMsg": "",
    "startDate": "Mar 20, 1974, 12:00:00 AM",
    "videoType": "動畫電影",
    "hasChineseWikiLink": false,
    "year": 1974
  },
  {
    "originalTitle": "タイガーマスク 黒い魔神",
    "chineseTitle": "虎面人（TV版第56話再編集）",
    "titleMsg": "",
    "startDate": "Mar 20, 1974, 12:00:00 AM",
    "videoType": "動畫電影",
    "hasChineseWikiLink": false,
    "year": 1974
  },
  {
    "originalTitle": "魔法のマコちゃん",
    "chineseTitle": "魔法人魚真子 （TV版第3話）",
    "titleMsg": "",
    "startDate": "Mar 20, 1974, 12:00:00 AM",
    "videoType": "動畫電影",
    "hasChineseWikiLink": false,
    "year": 1974
  },
  {
    "originalTitle": "キックの鬼",
    "chineseTitle": "無影腳 （TV版第11話）",
    "titleMsg": "",
    "startDate": "Mar 20, 1974, 12:00:00 AM",
    "videoType": "動畫電影",
    "hasChineseWikiLink": false,
    "year": 1974
  },
  {
    "originalTitle": "忍風カムイ外伝 月日貝の巻",
    "chineseTitle": "忍風KAMUI外傳 月日貝の巻",
    "titleMsg": "",
    "startDate": "Mar 20, 1974, 12:00:00 AM",
    "videoType": "動畫電影",
    "company": "TCJ動畫センター",
    "year": 1974
  },
  {
    "originalTitle": "アリババと40匹の盗賊",
    "chineseTitle": "阿里巴巴與四十大盜",
    "titleMsg": "",
    "startDate": "Jul 18, 1974, 12:00:00 AM",
    "videoType": "動畫電影",
    "hasChineseWikiLink": false,
    "year": 1974
  },
  {
    "originalTitle": "魔法のマコちゃん グラウンドの天使",
    "chineseTitle": "魔法人魚真子 TV版第28話",
    "titleMsg": "",
    "startDate": "Jul 18, 1974, 12:00:00 AM",
    "videoType": "動畫電影",
    "hasChineseWikiLink": false,
    "year": 1974
  },
  {
    "originalTitle": "アンデルセン物語 おやゆび姫",
    "chineseTitle": "安徒生童話故事（TV版第7-10話再編集）",
    "titleMsg": "",
    "startDate": "Jul 18, 1974, 12:00:00 AM",
    "videoType": "動畫電影",
    "hasChineseWikiLink": false,
    "year": 1974
  },
  {
    "originalTitle": "いなかっぺ大将 猛獣の中にわれ一人だス、オオ!ミステークだス",
    "chineseTitle": "鄉下仔出城（TV版再編集）",
    "titleMsg": "",
    "startDate": "Jul 24, 1974, 12:00:00 AM",
    "videoType": "動畫電影",
    "hasChineseWikiLink": false,
    "year": 1974
  },
  {
    "originalTitle": "みなしごハッチ 傷だらけのバレリーナ",
    "chineseTitle": "小蜜蜂 TV版第8話",
    "titleMsg": "",
    "startDate": "Jul 24, 1974, 12:00:00 AM",
    "videoType": "動畫電影",
    "hasChineseWikiLink": false,
    "year": 1974
  },
  {
    "originalTitle": "ヤスジのポルノラマ やっちまえ!!",
    "chineseTitle": "谷岡泰次的色情動畫 做吧!!",
    "titleMsg": "",
    "startDate": "Sep 24, 1974, 12:00:00 AM",
    "videoType": "動畫電影",
    "company": "東京テレビ動畫",
    "year": 1974
  },
  {
    "originalTitle": "いなかっぺ大将 猫も歩けば雀に当たるだス、当たるも当たらぬも時の運だス",
    "chineseTitle": "鄉下仔出城（TV版再編集）",
    "titleMsg": "",
    "startDate": "Dec 12, 1974, 12:00:00 AM",
    "videoType": "動畫電影",
    "hasChineseWikiLink": false,
    "year": 1974
  },
  {
    "originalTitle": "みなしごハッチ 忘れな草に願いをこめて",
    "chineseTitle": "小蜜蜂 TV版第74話",
    "titleMsg": "",
    "startDate": "Dec 12, 1974, 12:00:00 AM",
    "videoType": "動畫電影",
    "hasChineseWikiLink": false,
    "year": 1974
  },
  {
    "originalTitle": "樫の木モック",
    "chineseTitle": "木偶奇遇記",
    "titleMsg": "樫木莫克（原作：）",
    "startDate": "Jan 4, 1975, 12:00:00 AM",
    "endDate": "Dec 26, 1975, 12:00:00 AM",
    "videoType": "電視動畫",
    "company": "龍之子",
    "episodes": 52,
    "year": 1975
  },
  {
    "originalTitle": "ムーミン",
    "chineseTitle": "嚕嚕米",
    "titleMsg": "（第2作）",
    "startDate": "Jan 9, 1975, 12:00:00 AM",
    "endDate": "Dec 31, 1975, 12:00:00 AM",
    "videoType": "電視動畫",
    "company": "蟲Production",
    "episodes": 52,
    "year": 1975
  },
  {
    "originalTitle": "正義を愛する者 月光仮面",
    "chineseTitle": "月光假面",
    "titleMsg": "",
    "startDate": "Jan 10, 1975, 12:00:00 AM",
    "endDate": "Oct 2, 1975, 12:00:00 AM",
    "videoType": "電視動畫",
    "company": "ナック",
    "episodes": 39,
    "year": 1975
  },
  {
    "originalTitle": "海のトリトン",
    "chineseTitle": "海王子",
    "titleMsg": "",
    "startDate": "Apr 1, 1975, 1:00:00 AM",
    "endDate": "Sep 30, 1975, 12:00:00 AM",
    "videoType": "電視動畫",
    "company": "アニメーションスタッフルーム",
    "episodes": 27,
    "year": 1975
  },
  {
    "originalTitle": "魔法使いチャッピー",
    "chineseTitle": "魔法使恰比",
    "titleMsg": "",
    "startDate": "Apr 3, 1975, 12:00:00 AM",
    "endDate": "Dec 25, 1975, 12:00:00 AM",
    "videoType": "電視動畫",
    "company": "東映動畫",
    "episodes": 39,
    "year": 1975
  },
  {
    "originalTitle": "赤胴鈴之助",
    "chineseTitle": "赤胴鈴之助",
    "titleMsg": "",
    "startDate": "Apr 5, 1975, 12:00:00 AM",
    "endDate": "Mar 28, 1973, 12:00:00 AM",
    "videoType": "電視動畫",
    "company": "東京電影",
    "episodes": 52,
    "year": 1975
  },
  {
    "originalTitle": "アニメドキュメント ミュンヘンへの道",
    "chineseTitle": "動畫紀錄片 前往慕尼黑之路",
    "titleMsg": "",
    "startDate": "Apr 23, 1975, 12:00:00 AM",
    "endDate": "Aug 20, 1975, 12:00:00 AM",
    "videoType": "電視動畫",
    "company": "日本テレビ動畫",
    "episodes": 16,
    "year": 1975
  },
  {
    "originalTitle": "デビルマン",
    "chineseTitle": "惡魔人",
    "titleMsg": "",
    "startDate": "Jul 8, 1975, 12:00:00 AM",
    "endDate": "Mar 31, 1975, 12:00:00 AM",
    "videoType": "電視動畫",
    "company": "東映動畫",
    "episodes": 39,
    "year": 1975
  },
  {
    "originalTitle": "モンシェリCoCo",
    "chineseTitle": "酒釀櫻桃巧克力CoCo",
    "titleMsg": "",
    "startDate": "Aug 27, 1975, 12:00:00 AM",
    "endDate": "Nov 26, 1975, 12:00:00 AM",
    "videoType": "電視動畫",
    "company": "日本テレビ動畫",
    "episodes": 13,
    "year": 1975
  },
  {
    "originalTitle": "科学忍者隊ガッチャマン",
    "chineseTitle": "科學小飛俠",
    "titleMsg": "",
    "startDate": "Oct 1, 1975, 12:00:00 AM",
    "endDate": "Sep 29, 1974, 12:00:00 AM",
    "videoType": "電視動畫",
    "company": "龍之子",
    "episodes": 105,
    "year": 1975
  },
  {
    "originalTitle": "アストロガンガー",
    "chineseTitle": "鐵甲飛天俠",
    "titleMsg": "",
    "startDate": "Oct 4, 1975, 12:00:00 AM",
    "endDate": "Mar 28, 1973, 12:00:00 AM",
    "videoType": "電視動畫",
    "company": "ナック",
    "episodes": 26,
    "year": 1975
  },
  {
    "originalTitle": "かいけつタマゴン",
    "chineseTitle": "",
    "titleMsg": "",
    "startDate": "Oct 5, 1975, 12:00:00 AM",
    "endDate": "Sep 29, 1973, 12:00:00 AM",
    "videoType": "電視動畫",
    "company": "龍之子",
    "episodes": 308,
    "year": 1975
  },
  {
    "originalTitle": "ハゼドン",
    "chineseTitle": "水晶宮",
    "titleMsg": "",
    "startDate": "Oct 5, 1975, 12:00:00 AM",
    "endDate": "Mar 29, 1973, 12:00:00 AM",
    "videoType": "電視動畫",
    "company": "創映社",
    "episodes": 26,
    "year": 1975
  },
  {
    "originalTitle": "おんぶおばけ",
    "chineseTitle": "",
    "titleMsg": "",
    "startDate": "Oct 7, 1975, 12:00:00 AM",
    "endDate": "Sep 29, 1973, 12:00:00 AM",
    "videoType": "電視動畫",
    "company": "TCJ動畫センター",
    "episodes": 52,
    "year": 1975
  },
  {
    "originalTitle": "ど根性ガエル",
    "chineseTitle": "根性青蛙",
    "titleMsg": "",
    "startDate": "Oct 7, 1975, 12:00:00 AM",
    "endDate": "Sep 28, 1974, 12:00:00 AM",
    "videoType": "電視動畫",
    "company": "東京電影",
    "episodes": 103,
    "year": 1975
  },
  {
    "originalTitle": "マジンガーZ",
    "chineseTitle": "無敵鐵金剛",
    "titleMsg": "",
    "startDate": "Dec 3, 1975, 12:00:00 AM",
    "endDate": "Sep 1, 1974, 12:00:00 AM",
    "videoType": "電視動畫",
    "company": "東映動畫",
    "episodes": 92,
    "year": 1975
  },
  {
    "originalTitle": "かしの木モック",
    "chineseTitle": "樫木莫克（TV版第1話）",
    "titleMsg": "",
    "startDate": "Mar 12, 1976, 12:00:00 AM",
    "videoType": "動畫電影",
    "hasChineseWikiLink": false,
    "year": 1976
  },
  {
    "originalTitle": "みなしごハッチ ママにだかれて",
    "chineseTitle": "小蜜蜂 TV版第90-91話",
    "titleMsg": "",
    "startDate": "Mar 12, 1976, 12:00:00 AM",
    "videoType": "動畫電影",
    "hasChineseWikiLink": false,
    "year": 1976
  },
  {
    "originalTitle": "天才バカボン",
    "chineseTitle": "天才妙老爹 （TV版第17話）",
    "titleMsg": "",
    "startDate": "Mar 12, 1976, 12:00:00 AM",
    "videoType": "動畫電影",
    "hasChineseWikiLink": false,
    "year": 1976
  },
  {
    "originalTitle": "ながぐつ三銃士",
    "chineseTitle": "長靴貓西部劍客",
    "titleMsg": "",
    "startDate": "Mar 18, 1976, 12:00:00 AM",
    "videoType": "動畫電影",
    "hasChineseWikiLink": true,
    "year": 1976
  },
  {
    "originalTitle": "さるとびエッちゃん",
    "chineseTitle": "神奇小丫頭（TV版第1話）",
    "titleMsg": "",
    "startDate": "Mar 18, 1976, 12:00:00 AM",
    "videoType": "動畫電影",
    "hasChineseWikiLink": false,
    "year": 1976
  },
  {
    "originalTitle": "ムーミン",
    "chineseTitle": "嚕嚕米 （TV版第2話）",
    "titleMsg": "",
    "startDate": "Mar 18, 1976, 12:00:00 AM",
    "videoType": "動畫電影",
    "hasChineseWikiLink": false,
    "year": 1976
  },
  {
    "originalTitle": "魔犬ライナー0011変身せよ!",
    "chineseTitle": "魔犬萊納0011變身吧！",
    "titleMsg": "",
    "startDate": "Jul 16, 1976, 12:00:00 AM",
    "videoType": "動畫電影",
    "hasChineseWikiLink": false,
    "year": 1976
  },
  {
    "originalTitle": "魔法使いチャッピー",
    "chineseTitle": "魔法使恰比 （TV版第7話）",
    "titleMsg": "",
    "startDate": "Jul 16, 1976, 12:00:00 AM",
    "videoType": "動畫電影",
    "hasChineseWikiLink": false,
    "year": 1976
  },
  {
    "originalTitle": "国松さまのお通りだい",
    "chineseTitle": "萬能旋風兒（TV版第8話）",
    "titleMsg": "",
    "startDate": "Jul 16, 1976, 12:00:00 AM",
    "videoType": "動畫電影",
    "hasChineseWikiLink": false,
    "year": 1976
  },
  {
    "originalTitle": "かしの木モック ぼくはなかない",
    "chineseTitle": "樫木莫克 再編集版",
    "titleMsg": "",
    "startDate": "Jul 22, 1976, 12:00:00 AM",
    "videoType": "動畫電影",
    "hasChineseWikiLink": false,
    "year": 1976
  },
  {
    "originalTitle": "天才バカボン 別れはつらいものなのだ",
    "chineseTitle": "天才妙老爹 （TV版第29話）",
    "titleMsg": "",
    "startDate": "Jul 22, 1976, 12:00:00 AM",
    "videoType": "動畫電影",
    "hasChineseWikiLink": false,
    "year": 1976
  },
  {
    "originalTitle": "パンダコパンダ",
    "chineseTitle": "熊貓家族",
    "titleMsg": "",
    "startDate": "Dec 17, 1976, 12:00:00 AM",
    "videoType": "動畫電影",
    "company": "東京電影",
    "year": 1976
  },
  {
    "originalTitle": "バビル2世",
    "chineseTitle": "巴比倫2世",
    "titleMsg": "",
    "startDate": "Jan 1, 1977, 12:00:00 AM",
    "endDate": "Sep 24, 1977, 12:00:00 AM",
    "videoType": "電視動畫",
    "company": "東映動畫",
    "episodes": 39,
    "year": 1977
  },
  {
    "originalTitle": "けろっこデメタン",
    "chineseTitle": "小青蛙",
    "titleMsg": "",
    "startDate": "Jan 2, 1977, 12:00:00 AM",
    "endDate": "Sep 25, 1977, 12:00:00 AM",
    "videoType": "電視動畫",
    "company": "龍之子",
    "episodes": 39,
    "year": 1977
  },
  {
    "originalTitle": "山ねずみロッキーチャック",
    "chineseTitle": "森林小英雄",
    "titleMsg": "",
    "startDate": "Jan 7, 1977, 12:00:00 AM",
    "endDate": "Dec 30, 1977, 12:00:00 AM",
    "videoType": "電視動畫",
    "company": "瑞鷹映像",
    "episodes": 52,
    "year": 1977
  },
  {
    "originalTitle": "ジャングル黒べえ",
    "chineseTitle": "黃毛仔",
    "titleMsg": "",
    "startDate": "Mar 2, 1977, 12:00:00 AM",
    "endDate": "Sep 28, 1977, 12:00:00 AM",
    "videoType": "電視動畫",
    "company": "東京電影",
    "episodes": 61,
    "year": 1977
  },
  {
    "originalTitle": "ドラえもん",
    "chineseTitle": "哆啦A夢",
    "titleMsg": "（第1作）",
    "startDate": "Apr 1, 1977, 12:00:00 AM",
    "endDate": "Sep 30, 1977, 12:00:00 AM",
    "videoType": "電視動畫",
    "company": "日本テレビ動畫",
    "episodes": 52,
    "year": 1977
  },
  {
    "originalTitle": "ワンサくん",
    "chineseTitle": "",
    "titleMsg": "",
    "startDate": "Apr 2, 1977, 12:00:00 AM",
    "endDate": "Sep 24, 1973, 12:00:00 AM",
    "videoType": "電視動畫",
    "company": "蟲Production",
    "episodes": 26,
    "year": 1977
  },
  {
    "originalTitle": "荒野の少年イサム",
    "chineseTitle": "大漠小英雄",
    "titleMsg": "",
    "startDate": "Apr 4, 1977, 12:00:00 AM",
    "endDate": "Mar 27, 1974, 12:00:00 AM",
    "videoType": "電視動畫",
    "company": "東京電影",
    "episodes": 52,
    "year": 1977
  },
  {
    "originalTitle": "ミクロイドS",
    "chineseTitle": "玲瓏三勇士",
    "titleMsg": "",
    "startDate": "Apr 7, 1977, 12:00:00 AM",
    "endDate": "Oct 6, 1977, 12:00:00 AM",
    "videoType": "電視動畫",
    "company": "東映動畫",
    "episodes": 26,
    "year": 1977
  },
  {
    "originalTitle": "ゼロテスター",
    "chineseTitle": "英勇無敵號",
    "titleMsg": "",
    "startDate": "Oct 1, 1977, 12:00:00 AM",
    "endDate": "Dec 30, 1974, 12:00:00 AM",
    "videoType": "電視動畫",
    "company": "創映社",
    "episodes": 66,
    "year": 1977
  },
  {
    "originalTitle": "ミラクル少女リミットちゃん",
    "chineseTitle": "奇蹟少女理美",
    "titleMsg": "",
    "startDate": "Oct 1, 1977, 12:00:00 AM",
    "endDate": "Mar 25, 1974, 12:00:00 AM",
    "videoType": "電視動畫",
    "company": "東映動畫",
    "episodes": 25,
    "year": 1977
  },
  {
    "originalTitle": "新造人間キャシャーン",
    "chineseTitle": "再造人卡辛",
    "titleMsg": "",
    "startDate": "Oct 2, 1977, 12:00:00 AM",
    "endDate": "Jun 25, 1974, 12:00:00 AM",
    "videoType": "電視動畫",
    "company": "龍之子",
    "episodes": 35,
    "year": 1977
  },
  {
    "originalTitle": "空手バカ一代",
    "chineseTitle": "",
    "titleMsg": "",
    "startDate": "Oct 3, 1977, 12:00:00 AM",
    "endDate": "Sep 25, 1974, 12:00:00 AM",
    "videoType": "電視動畫",
    "company": "東京電影",
    "episodes": 47,
    "year": 1977
  },
  {
    "originalTitle": "ドロロンえん魔くん",
    "chineseTitle": "咚隆隆炎魔君",
    "titleMsg": "",
    "startDate": "Oct 4, 1977, 12:00:00 AM",
    "endDate": "Mar 28, 1974, 12:00:00 AM",
    "videoType": "電視動畫",
    "company": "東映動畫",
    "episodes": 25,
    "year": 1977
  },
  {
    "originalTitle": "エースをねらえ!",
    "chineseTitle": "網球甜心",
    "titleMsg": "",
    "startDate": "Oct 5, 1977, 12:00:00 AM",
    "endDate": "Mar 29, 1974, 12:00:00 AM",
    "videoType": "電視動畫",
    "company": "東京電影",
    "episodes": 26,
    "year": 1977
  },
  {
    "originalTitle": "冒険コロボックル",
    "chineseTitle": "",
    "titleMsg": "",
    "startDate": "Oct 6, 1977, 12:00:00 AM",
    "endDate": "Mar 30, 1974, 12:00:00 AM",
    "videoType": "電視動畫",
    "company": "EIKEN",
    "episodes": 26,
    "year": 1977
  },
  {
    "originalTitle": "侍ジャイアンツ",
    "chineseTitle": "魔投手",
    "titleMsg": "",
    "startDate": "Oct 7, 1977, 12:00:00 AM",
    "endDate": "Sep 29, 1974, 12:00:00 AM",
    "videoType": "電視動畫",
    "company": "東京電影",
    "episodes": 48,
    "year": 1977
  },
  {
    "originalTitle": "キューティーハニー",
    "chineseTitle": "甜心戰士",
    "titleMsg": "",
    "startDate": "Oct 13, 1977, 12:00:00 AM",
    "endDate": "Mar 30, 1974, 12:00:00 AM",
    "videoType": "電視動畫",
    "company": "東映動畫",
    "episodes": 25,
    "year": 1977
  },
  {
    "originalTitle": "パンダコパンダ 雨ふりサーカスの巻",
    "chineseTitle": "熊貓家族 雨中的馬戲團",
    "titleMsg": "",
    "startDate": "Mar 17, 1978, 12:00:00 AM",
    "videoType": "動畫電影",
    "hasChineseWikiLink": true,
    "year": 1978
  },
  {
    "originalTitle": "ジャングル黒べえ",
    "chineseTitle": "黃毛仔 （TV版第2話B part）",
    "titleMsg": "",
    "startDate": "Mar 17, 1978, 12:00:00 AM",
    "videoType": "動畫電影",
    "hasChineseWikiLink": false,
    "year": 1978
  },
  {
    "originalTitle": "パンダの大冒険",
    "chineseTitle": "熊貓的大冒險",
    "titleMsg": "",
    "startDate": "Mar 17, 1978, 12:00:00 AM",
    "videoType": "動畫電影",
    "hasChineseWikiLink": false,
    "year": 1978
  },
  {
    "originalTitle": "ひみつのアッコちゃん",
    "chineseTitle": "甜蜜小天使（TV版第34話）",
    "titleMsg": "",
    "startDate": "Mar 17, 1978, 12:00:00 AM",
    "videoType": "動畫電影",
    "hasChineseWikiLink": false,
    "year": 1978
  },
  {
    "originalTitle": "バビル2世",
    "chineseTitle": "巴比倫2世 （TV版第2話）",
    "titleMsg": "",
    "startDate": "Mar 17, 1978, 12:00:00 AM",
    "videoType": "動畫電影",
    "hasChineseWikiLink": false,
    "year": 1978
  },
  {
    "originalTitle": "マジンガーZ",
    "chineseTitle": "無敵鐵金剛（TV版第5話）",
    "titleMsg": "",
    "startDate": "Mar 17, 1978, 12:00:00 AM",
    "videoType": "動畫電影",
    "hasChineseWikiLink": false,
    "year": 1978
  },
  {
    "originalTitle": "哀しみのベラドンナ",
    "chineseTitle": "哀傷的Belladonna",
    "titleMsg": "",
    "startDate": "Jun 30, 1978, 12:00:00 AM",
    "videoType": "動畫電影",
    "company": "蟲Production",
    "year": 1978
  },
  {
    "originalTitle": "マジンガーZ対デビルマン",
    "chineseTitle": "無敵鐵金剛對惡魔人",
    "titleMsg": "",
    "startDate": "Jul 18, 1978, 12:00:00 AM",
    "videoType": "動畫電影",
    "hasChineseWikiLink": false,
    "year": 1978
  },
  {
    "originalTitle": "魔法使いサリー",
    "chineseTitle": "魔法使莎莉 （TV版第89話）",
    "titleMsg": "",
    "startDate": "Jul 18, 1978, 12:00:00 AM",
    "videoType": "動畫電影",
    "hasChineseWikiLink": false,
    "year": 1978
  },
  {
    "originalTitle": "バビル2世 赤ちゃんは超能力者",
    "chineseTitle": "巴比倫2世 （TV版第21話）",
    "titleMsg": "",
    "startDate": "Jul 18, 1978, 12:00:00 AM",
    "videoType": "動畫電影",
    "hasChineseWikiLink": false,
    "year": 1978
  },
  {
    "originalTitle": "科学忍者隊ガッチャマン 火の鳥対人喰い竜",
    "chineseTitle": "科學小飛俠 TV版第22話",
    "titleMsg": "",
    "startDate": "Jul 28, 1978, 12:00:00 AM",
    "videoType": "動畫電影",
    "hasChineseWikiLink": false,
    "year": 1978
  },
  {
    "originalTitle": "山ねずみロッキーチャック",
    "chineseTitle": "森林小英雄 （TV版第3話）",
    "titleMsg": "",
    "startDate": "Jul 28, 1978, 12:00:00 AM",
    "videoType": "動畫電影",
    "hasChineseWikiLink": false,
    "year": 1978
  },
  {
    "originalTitle": "科学忍者隊ガッチャマン 電子怪獣レンジラー",
    "chineseTitle": "科學小飛俠 TV版第37話",
    "titleMsg": "",
    "startDate": "Dec 20, 1978, 12:00:00 AM",
    "videoType": "動畫電影",
    "hasChineseWikiLink": false,
    "year": 1978
  },
  {
    "originalTitle": "山ねずみロッキーチャック がんばれチャタラー",
    "chineseTitle": "森林小英雄 （TV版第39話）",
    "titleMsg": "",
    "startDate": "Dec 20, 1978, 12:00:00 AM",
    "videoType": "動畫電影",
    "hasChineseWikiLink": false,
    "year": 1978
  },
  {
    "originalTitle": "エースをねらえ! テニス王国のシンデレラ",
    "chineseTitle": "網球甜心 TV版第1話",
    "titleMsg": "",
    "startDate": "Dec 20, 1978, 12:00:00 AM",
    "videoType": "動畫電影",
    "hasChineseWikiLink": false,
    "year": 1978
  },
  {
    "originalTitle": "侍ジャイアンツ ほえろバンババン",
    "chineseTitle": "魔投手 TV版第1話",
    "titleMsg": "",
    "startDate": "Dec 20, 1978, 12:00:00 AM",
    "videoType": "動畫電影",
    "hasChineseWikiLink": false,
    "year": 1978
  },
  {
    "originalTitle": "アルプスの少女ハイジ",
    "chineseTitle": "阿爾卑斯山的少女海蒂",
    "titleMsg": "",
    "startDate": "Jan 6, 1979, 12:00:00 AM",
    "endDate": "Dec 29, 1979, 12:00:00 AM",
    "videoType": "電視動畫",
    "company": "日本動畫公司",
    "episodes": 52,
    "year": 1979
  },
  {
    "originalTitle": "柔道讃歌",
    "chineseTitle": "柔道讃歌",
    "titleMsg": "",
    "startDate": "Apr 1, 1979, 12:00:00 AM",
    "endDate": "Sep 30, 1979, 12:00:00 AM",
    "videoType": "電視動畫",
    "company": "東京電影",
    "episodes": 27,
    "year": 1979
  },
  {
    "originalTitle": "チャージマン研!",
    "chineseTitle": "ChargeMan研！",
    "titleMsg": "",
    "startDate": "Apr 1, 1979, 12:00:00 AM",
    "endDate": "Jun 28, 1979, 12:00:00 AM",
    "videoType": "電視動畫",
    "company": "ナック",
    "episodes": 65,
    "year": 1979
  },
  {
    "originalTitle": "星の子ポロン",
    "chineseTitle": "星之子波倫",
    "titleMsg": "",
    "startDate": "Apr 1, 1979, 12:00:00 AM",
    "endDate": "Apr 4, 1975, 12:00:00 AM",
    "videoType": "電視動畫",
    "company": "日本動畫",
    "episodes": 260,
    "year": 1979
  },
  {
    "originalTitle": "魔女っ子メグちゃん",
    "chineseTitle": "仙女下凡",
    "titleMsg": "",
    "startDate": "Apr 1, 1979, 12:00:00 AM",
    "endDate": "Sep 29, 1975, 12:00:00 AM",
    "videoType": "電視動畫",
    "company": "東映動畫",
    "episodes": 72,
    "year": 1979
  },
  {
    "originalTitle": "ダメおやじ",
    "chineseTitle": "",
    "titleMsg": "",
    "startDate": "Apr 2, 1979, 12:00:00 AM",
    "endDate": "Oct 9, 1979, 12:00:00 AM",
    "videoType": "電視動畫",
    "company": "ナック",
    "episodes": 26,
    "year": 1979
  },
  {
    "originalTitle": "小さなバイキングビッケ",
    "chineseTitle": "北海小英雄",
    "titleMsg": "",
    "startDate": "Apr 3, 1979, 12:00:00 AM",
    "endDate": "Sep 24, 1975, 12:00:00 AM",
    "videoType": "電視動畫",
    "company": "日本動畫公司",
    "episodes": 77,
    "year": 1979
  },
  {
    "originalTitle": "ゲッターロボ",
    "chineseTitle": "蓋特機器人",
    "titleMsg": "",
    "startDate": "Apr 4, 1979, 12:00:00 AM",
    "endDate": "May 8, 1975, 12:00:00 AM",
    "videoType": "電視動畫",
    "company": "東映動畫",
    "episodes": 51,
    "year": 1979
  },
  {
    "originalTitle": "ガンとゴン",
    "chineseTitle": "",
    "titleMsg": "",
    "startDate": "Apr 5, 1979, 12:00:00 AM",
    "endDate": "Aug 13, 1975, 12:00:00 AM",
    "videoType": "電視動畫",
    "company": "日本動畫、時報映畫社",
    "episodes": 260,
    "year": 1979
  },
  {
    "originalTitle": "昆虫物語 新みなしごハッチ",
    "chineseTitle": "新小蜜蜂",
    "titleMsg": "",
    "startDate": "Apr 5, 1979, 12:00:00 AM",
    "endDate": "Sep 25, 1979, 12:00:00 AM",
    "videoType": "電視動畫",
    "company": "龍之子",
    "episodes": 26,
    "year": 1979
  },
  {
    "originalTitle": "となりのたまげ太くん",
    "chineseTitle": "",
    "titleMsg": "",
    "startDate": "Apr 5, 1979, 12:00:00 AM",
    "endDate": "Jun 27, 1975, 12:00:00 AM",
    "videoType": "電視動畫",
    "company": "零工作室",
    "episodes": 60,
    "year": 1979
  },
  {
    "originalTitle": "星の子チョビン",
    "chineseTitle": "星星王子",
    "titleMsg": "",
    "startDate": "Apr 5, 1979, 12:00:00 AM",
    "endDate": "Sep 27, 1974, 12:00:00 AM",
    "videoType": "電視動畫",
    "company": "零工作室",
    "episodes": 26,
    "year": 1979
  },
  {
    "originalTitle": "グレートマジンガー",
    "chineseTitle": "金剛大魔神",
    "titleMsg": "",
    "startDate": "Sep 8, 1979, 12:00:00 AM",
    "endDate": "Sep 28, 1975, 12:00:00 AM",
    "videoType": "電視動畫",
    "company": "東映動畫",
    "episodes": 56,
    "year": 1979
  },
  {
    "originalTitle": "ウリクペン救助隊",
    "chineseTitle": "雜牌拯救隊",
    "titleMsg": "",
    "startDate": "Sep 30, 1979, 12:00:00 AM",
    "endDate": "Mar 29, 1975, 12:00:00 AM",
    "videoType": "電視動畫",
    "company": "龍之子",
    "episodes": 22,
    "year": 1979
  },
  {
    "originalTitle": "ジムボタン",
    "chineseTitle": "吉姆·克諾普夫",
    "titleMsg": "",
    "startDate": "Oct 4, 1979, 12:00:00 AM",
    "endDate": "Mar 28, 1975, 12:00:00 AM",
    "videoType": "電視動畫",
    "company": "EIKEN",
    "episodes": 26,
    "year": 1979
  },
  {
    "originalTitle": "破裏拳ポリマー",
    "chineseTitle": "破裡拳旋風俠",
    "titleMsg": "",
    "startDate": "Oct 4, 1979, 12:00:00 AM",
    "endDate": "Mar 28, 1975, 12:00:00 AM",
    "videoType": "電視動畫",
    "company": "龍之子",
    "episodes": 26,
    "year": 1979
  },
  {
    "originalTitle": "はじめ人間ギャートルズ",
    "chineseTitle": "山林小獵人",
    "titleMsg": "",
    "startDate": "Oct 5, 1979, 12:00:00 AM",
    "endDate": "Aug 3, 2143, 12:00:00 AM",
    "videoType": "電視動畫",
    "company": "東京電影",
    "episodes": 77,
    "year": 1979
  },
  {
    "originalTitle": "宇宙戦艦ヤマト",
    "chineseTitle": "宇宙戰艦大和號",
    "titleMsg": "",
    "startDate": "Oct 6, 1979, 12:00:00 AM",
    "endDate": "Mar 30, 1976, 12:00:00 AM",
    "videoType": "電視動畫",
    "company": "オフィスアカデミー",
    "episodes": 26,
    "year": 1979
  },
  {
    "originalTitle": "てんとう虫の歌",
    "chineseTitle": "瓢蟲之歌",
    "titleMsg": "",
    "startDate": "Oct 6, 1979, 12:00:00 AM",
    "endDate": "Sep 26, 1976, 12:00:00 AM",
    "videoType": "電視動畫",
    "company": "龍之子",
    "episodes": 104,
    "year": 1979
  },
  {
    "originalTitle": "カリメロ",
    "chineseTitle": "Duck Chick探險隊 / 精靈採訪隊Calimero",
    "titleMsg": "",
    "startDate": "Oct 15, 1979, 12:00:00 AM",
    "endDate": "Sep 30, 1975, 12:00:00 AM",
    "videoType": "電視動畫",
    "company": "東映動畫",
    "episodes": 45,
    "year": 1979
  }
]
